vyoma_download/__init__.py
vyoma_download/cli.py
vyoma_download/edmingle.py
vyoma_download/utils.py
vyoma_download/verbose_logger.py
vyoma_download/vyoma.deprecated.py
vyoma_download/vyoma.py
vyoma_download-1.0.1.dist-info/AUTHORS.rst
vyoma_download-1.0.1.dist-info/LICENSE
vyoma_download-1.0.1.dist-info/METADATA
vyoma_download-1.0.1.dist-info/WHEEL
vyoma_download-1.0.1.dist-info/entry_points.txt
vyoma_download-1.0.1.dist-info/top_level.txt
vyoma_download-1.0.1.dist-info/RECORD
