Metadata-Version: 2.1
Name: vyoma-download
Version: 1.0.1
Summary: Download course contents from sanskritfromhome.org
Home-page: https://github.com/hrishikeshrt/vyoma_download
Author: Hrishikesh Terdalkar
Author-email: hrishikeshrt@linuxmail.org
License: MIT license
Keywords: vyoma_download
Platform: UNKNOWN
Classifier: Development Status :: 4 - Beta
Classifier: License :: OSI Approved :: MIT License
Classifier: Natural Language :: English
Classifier: Topic :: Internet
Classifier: Topic :: Utilities
Classifier: Programming Language :: Python :: 3
Classifier: Programming Language :: Python :: 3.6
Classifier: Programming Language :: Python :: 3.7
Classifier: Programming Language :: Python :: 3.8
Classifier: Programming Language :: Python :: 3.9
Requires-Python: >=3.6
License-File: LICENSE
License-File: AUTHORS.rst
Requires-Dist: requests
Requires-Dist: requests-downloader
Requires-Dist: beautifulsoup4
Requires-Dist: tabulate
